[
  {
    "id": 21,
    "title": "Tikka Masala Rápido com Brócolos",
    "category": "Peixe e Conservas",
    "origin": "Índia e Médio Oriente",
    "dynamics": [
      "Uma Panela",
      "Amigo do Congelador"
    ],
    "time": "35 min",
    "ingredients": [
      {
        "qty": "400",
        "unit": "g",
        "name": "peixe branco firme",
        "prep": "cortado em cubos tamboril ou maruca"
      },
      {
        "qty": null,
        "unit": null,
        "name": "base masala rápida: 150 ml de polpa de tomate rústica + 1 iogurte grego natural",
        "prep": "à temperatura ambiente"
      },
      {
        "qty": "1",
        "unit": null,
        "name": "colher de chá de garam masala e 1/2 colher de chá de cominhos em pó",
        "prep": null
      },
      {
        "qty": null,
        "unit": null,
        "name": "brócolos",
        "prep": "cortados em floretes pequenos, alho e gengibre fresco ralado"
      }
    ],
    "instructions": [
      "Numa panela, salteie o alho e o gengibre ralado com as especiarias até libertarem os seus óleos essenciais (1 minuto).",
      "Junte a polpa de tomate e deixe apurar até escurecer ligeiramente. Adicione os brócolos e o peixe, cobrindo com o molho e uma gota de água quente. Tape durante 10 minutos.",
      "O truque para não talhar o iogurte: desligue o lume completamente. Junte duas colheres do molho quente ao iogurte frio numa taça para igualar as temperaturas, e só depois verta o iogurte para o tacho. O molho ficará de um rosa sedoso digno de chef."
    ],
    "baby_adaptation": "As especiarias limpas (sem picante) são fantásticas para a diversificação do palato! A cremosidade deste molho rosa, doce e ácido, é excelente para disfarçar legumes como os brócolos. Super macio de engolir!",
    "pingo_doce_link": "https://www.pingodoce.pt/on/demandware.store/Sites-pingo-doce-Site/default/Search-Show?q=Tikka+Masala"
  },
  {
    "id": 22,
    "title": "Dhal de Lentilhas Laranjas com Atum (Papa do Médio Oriente)",
    "category": "Peixe e Conservas",
    "origin": "Índia e Médio Oriente",
    "dynamics": [
      "Conforto",
      "Amigo do Congelador"
    ],
    "time": "30 min",
    "ingredients": [
      {
        "qty": "2",
        "unit": "chávena",
        "name": "lentilhas vermelhas ou laranjas",
        "prep": null
      },
      {
        "qty": "2",
        "unit": "lata",
        "name": "atum ao natural firme",
        "prep": null
      },
      {
        "qty": null,
        "unit": null,
        "name": "óleo de coco",
        "prep": "laminado ou azeite"
      },
      {
        "qty": null,
        "unit": null,
        "name": "cúrcuma e coentros",
        "prep": "picados açafrão-das-índias"
      }
    ],
    "instructions": [
      "Elevar a lentilha requer bases aromáticas: num tacho, faça estalar as sementes de mostarda e o gengibre no óleo de coco quente. Junte a cúrcuma.",
      "Verta as lentilhas com o dobro do seu peso em água ou caldo vegetal. Ferva suavemente 15 a 20 minutos. Sem casca visível, elas vão explodir num puré macio e dourado denso.",
      "No final, envolva os suculentos flocos de atum (sem água) e muitos coentros."
    ],
    "baby_adaptation": "As lentilhas laranjas são um segredo da nutrição — riquíssimas em ferro e sem a pele rija que causa gases. Esta é a papa caseira perfeita, repleta de proteínas, para as gengivas pequenas.",
    "pingo_doce_link": "https://www.pingodoce.pt/on/demandware.store/Sites-pingo-doce-Site/default/Search-Show?q=Dhal+Lentilhas"
  },
  {
    "id": 23,
    "title": "Koftas (Almôndegas/Kebab) de Salmão com Molho de Hortelã",
    "category": "Peixe e Conservas",
    "origin": "Índia e Médio Oriente",
    "dynamics": [
      "Uma Panela",
      "Express"
    ],
    "time": "25 min",
    "ingredients": [
      {
        "qty": "400",
        "unit": "g",
        "name": "salmão",
        "prep": "picado à faca bem fininho sem espinhas nem pele"
      },
      {
        "qty": null,
        "unit": null,
        "name": "miolo de pão esfarelado",
        "prep": "ou panko"
      },
      {
        "qty": null,
        "unit": null,
        "name": "raspa de limão",
        "prep": null
      },
      {
        "qty": null,
        "unit": null,
        "name": "molho adulto: iogurte grego",
        "prep": "ralado e escorrido, hortelã fresca picada"
      }
    ],
    "instructions": [
      "Dica: pique o peixe à faca para preservar a textura, em vez de o triturar até pasta! Numa taça fria, una intimamente o salmão com o pão, a raspa fina de limão, o ovo e os cominhos.",
      "Molde com as mãos rolos ao estilo kebab (cerca de 8 cm). Coloque no frio durante 15 minutos para firmarem.",
      "Asse num tabuleiro forrado e levemente untado no forno a 200 °C durante 10 a 12 minutos (não mais, o salmão seca rapidamente)."
    ],
    "baby_adaptation": "A forma alongada destas koftas é excelente para a mão da criança morder sem perder. Não afogue a porção da criança no molho frio de hortelã, para evitar o choque térmico com a carne quente.",
    "pingo_doce_link": "https://www.pingodoce.pt/on/demandware.store/Sites-pingo-doce-Site/default/Search-Show?q=Koftas"
  },
  {
    "id": 24,
    "title": "Orzotto de Tomate e Atum (Risotto Rápido de Massa)",
    "category": "Peixe e Conservas",
    "origin": "Mediterrânica Geral",
    "dynamics": [
      "Uma Panela"
    ],
    "time": "20 min",
    "ingredients": [
      {
        "qty": "1",
        "unit": "chávena",
        "name": "cheia de massa orzo",
        "prep": "pevide grossa"
      },
      {
        "qty": "1",
        "unit": null,
        "name": "cebola",
        "prep": "refogada muito finamente"
      },
      {
        "qty": "1/2",
        "unit": null,
        "name": "courgette ou beringela",
        "prep": "em cubos pequenos"
      },
      {
        "qty": "2",
        "unit": "lata",
        "name": "atum em posta gorda",
        "prep": null
      },
      {
        "qty": null,
        "unit": null,
        "name": "caldo vegetal",
        "prep": null
      },
      {
        "qty": "1",
        "unit": null,
        "name": "colherada de mascarpone ou natas gordas",
        "prep": "ralado"
      }
    ],
    "instructions": [
      "Trate a massa como um nobre risotto: frite ligeiramente o orzo na base de azeite e cebola quente durante 2 minutos, a rolar no tacho.",
      "Vá juntando o líquido fervente pouco a pouco: adicione o tomate e conchas de caldo. A meio, introduza a courgette.",
      "A absorção total demora apenas 14 minutos em ebulição calma. Apague o lume! Envolva o mascarpone ou as natas e o atum, deixando que este se desfaça pelo calor retido no tacho.",
      "Coroe cada prato com parmesão ralado na hora."
    ],
    "baby_adaptation": "As massinhas orzo escorregam pela garganta sem requerer mastigações difíceis. Uma textura luxuosa, húmida e calórica.",
    "pingo_doce_link": "https://www.pingodoce.pt/on/demandware.store/Sites-pingo-doce-Site/default/Search-Show?q=Orzotto"
  },
  {
    "id": 25,
    "title": "Paella Rasa Rápida de Peixe Branco",
    "category": "Peixe e Conservas",
    "origin": "Mediterrânica Geral",
    "dynamics": [
      "Uma Panela/Tabuleiro"
    ],
    "time": "35 min",
    "ingredients": [
      {
        "qty": "1,5",
        "unit": "chávena",
        "name": "arroz e carolino para paelha",
        "prep": null
      },
      {
        "qty": null,
        "unit": null,
        "name": "tiras coloridas de pimentos",
        "prep": "assados e descascados"
      },
      {
        "qty": null,
        "unit": null,
        "name": "caldo sublime de marisco ou de peixe caseiro",
        "prep": null
      },
      {
        "qty": null,
        "unit": null,
        "name": "fios de açafrão em pistilos",
        "prep": "ou colorau para substituto"
      }
    ],
    "instructions": [
      "Uma paella real precisa de largura: use a sua maior e mais achatada frigideira que vá ao forno ou fique no fogão. Faça a base com azeite, pimentos suados e o arroz.",
      "Regra vitalícia do chef espanhol: quando colocar o caldo aromático sobre o arroz, NUNCA mais mexa a colher no tacho! Deixe a fervura cozer devagar durante 18 minutos até formar o 'socarrat' — o estaladiço do fundo.",
      "A 5 minutos do fim, disponha as lascas ricas do peixe escolhido por cima, abafando rapidamente se a água secar. Sirva quente diretamente da chapa."
    ],
    "baby_adaptation": "O arroz seco e tostado da paella pode precisar de uma ou duas colheres de caldo quente misturadas na taça do bebé, para evitar o engasgo com os bagos mais granulosos. O peixe, por não ser mexido, mantém-se inteiro e fácil de identificar no prato.",
    "pingo_doce_link": "https://www.pingodoce.pt/on/demandware.store/Sites-pingo-doce-Site/default/Search-Show?q=Paella"
  },
  {
    "id": 26,
    "title": "Meia Desfeita de Grão Rica com Ovo Cozido e Pimentão",
    "category": "Base de Leguminosas / Vegetariano",
    "origin": "Portuguesa",
    "dynamics": [
      "Express"
    ],
    "time": "15 min",
    "ingredients": [
      {
        "qty": "1",
        "unit": "frasco",
        "name": "grande de grão-de-bico biológico",
        "prep": "cozido 400g"
      },
      {
        "qty": "4",
        "unit": null,
        "name": "ovos l",
        "prep": null
      },
      {
        "qty": "1/2",
        "unit": null,
        "name": "cebola roxa",
        "prep": "picada"
      },
      {
        "qty": "1",
        "unit": "dente",
        "name": "alho",
        "prep": "esmagado"
      },
      {
        "qty": "1",
        "unit": null,
        "name": "colher de café de pimentão doce fumado",
        "prep": "paprika"
      },
      {
        "qty": null,
        "unit": null,
        "name": "salsa fresca farta",
        "prep": "picada na hora, azeite virgem extra perfumado, vinagre de maçã ou de vinho"
      }
    ],
    "instructions": [
      "Coza os ovos à precisão: 9 minutos para uma gema firme mas elástica. Descasque sob água fria e lasque grosseiramente.",
      "Aqueça uma sertã ao rubro apenas com um fio de azeite e deite o grão escorrido, o alho e o pimentão fumado. Salteie em fogo vivo durante 3 minutos curtos para criar uma capa tostada e umami.",
      "Retire para a travessa, lance a cebola, os ovos, um fio de azeite do galheteiro, um jacto de vinagre e salsa em manto. Envolva respeitando o ovo."
    ],
    "baby_adaptation": "A meia desfeita do bebé exige garfo! Esmague o grão ativamente até virar um puré com textura. Omita da taça da criança a acidez do vinagre cru e a cebola crua.",
    "pingo_doce_link": "https://www.pingodoce.pt/on/demandware.store/Sites-pingo-doce-Site/default/Search-Show?q=Meia+Desfeita+Gr%C3%A3o"
  },
  {
    "id": 27,
    "title": "Ervilhas Estufadas com Ovos Escalfados e Fumados",
    "category": "Base de Leguminosas / Vegetariano",
    "origin": "Portuguesa",
    "dynamics": [
      "Uma Panela"
    ],
    "time": "25 min",
    "ingredients": [
      {
        "qty": "400",
        "unit": "g",
        "name": "ervilhas extrafinas congeladas",
        "prep": null
      },
      {
        "qty": "4",
        "unit": null,
        "name": "ovos com gema laranja",
        "prep": null
      },
      {
        "qty": "1",
        "unit": null,
        "name": "cebola e 2 dentes de alho",
        "prep": "picados"
      },
      {
        "qty": null,
        "unit": null,
        "name": "pimentão doce fumado espanhol",
        "prep": "para emular os fumos rústicos do chouriço ausente"
      },
      {
        "qty": "2",
        "unit": null,
        "name": "colheres de polpa de tomate",
        "prep": "em pedaços maduros, coentros ou hortelã"
      }
    ],
    "instructions": [
      "Num tacho raso de paredes altas, estute a cebola e o alho suavemente num fundo de azeite temperado com o pimentão fumado (que fingirá carnes presuntas nesta refeição verde).",
      "Adicione o tomate e de seguida as ervilhas ainda congeladas. Verta apenas meia chávena de caldo quente (para não empoçar), tape e deixe o vapor atuar durante 10 minutos.",
      "Abra pequenas concavidades delicadas no tapete de ervilhas e parta um ovo inteiro em cada uma. Tape o tacho com paciência sem mexer, deixando o calor médio pochar os ovos na humidade doce das ervilhas (5 a 8 minutos). Finalize com coentros frescos."
    ],
    "baby_adaptation": "Cuidado com o ovo escalfado para bebés! O ovo do bebé deve cozer bem — 10 a 12 minutos — sem centro pastoso, para eliminar qualquer risco de salmonella. Esmague as ervilhas para evitar o engasgo com as esferas inteiras.",
    "pingo_doce_link": "https://www.pingodoce.pt/on/demandware.store/Sites-pingo-doce-Site/default/Search-Show?q=Ervilhas+com+Ovos"
  },
  {
    "id": 28,
    "title": "Feijoada Rápida Umami de Cogumelos e Couve",
    "category": "Base de Leguminosas / Vegetariano",
    "origin": "Portuguesa",
    "dynamics": [
      "Conforto",
      "Amigo do Congelador"
    ],
    "time": "35 min",
    "ingredients": [
      {
        "qty": "1",
        "unit": "frasco",
        "name": "ou lata xl de feijão vermelho robusto",
        "prep": null
      },
      {
        "qty": "300",
        "unit": "g",
        "name": "mistura de cogumelos em fatias largas",
        "prep": "brancos e portobello"
      },
      {
        "qty": "1",
        "unit": "folha",
        "name": "louro",
        "prep": null
      },
      {
        "qty": "1",
        "unit": null,
        "name": "colher de sobremesa de molho de soja escuro",
        "prep": "segredo umami"
      },
      {
        "qty": "2",
        "unit": null,
        "name": "cenouras",
        "prep": "em meias-luas finas, folha de repolho ou couve tenra"
      },
      {
        "qty": null,
        "unit": null,
        "name": "alho",
        "prep": "picado, cominhos moídos, azeite"
      }
    ],
    "instructions": [
      "Esta feijoada sem enchidos ganha o seu peso nos cogumelos. Num tacho quente: azeite, alho e louro! Deixe dourar bem o cogumelo até minguar as suas águas, deglace com o molho de soja e os cominhos.",
      "Introduza a cenoura, a couve rasgada pelas mãos e o feijão com um pouco do líquido da lata para ajudar a ligar o molho. Cubra com caldo ou água quente.",
      "Reduza para lume médio e deixe tudo espessar durante um longo murmúrio de 20 minutos."
    ],
    "baby_adaptation": "O feijão vermelho rústico deve ser partido para BLW. Retire a porção do bebé antes de adicionar o molho de soja ao cogumelo. O cogumelo bem cozido passa perfeitamente como carne tenra ao morder das gengivas.",
    "pingo_doce_link": "https://www.pingodoce.pt/on/demandware.store/Sites-pingo-doce-Site/default/Search-Show?q=Feijoada+Vegetariana"
  },
  {
    "id": 29,
    "title": "Rancho Vegetariano Profundo com Grão e Macarronete",
    "category": "Base de Leguminosas / Vegetariano",
    "origin": "Portuguesa",
    "dynamics": [
      "Conforto",
      "Amigo do Congelador"
    ],
    "time": "35 min",
    "ingredients": [
      {
        "qty": "1",
        "unit": "lata",
        "name": "grão-de-bico",
        "prep": "cozido"
      },
      {
        "qty": "1,5",
        "unit": "chávena",
        "name": "macarronete ou massa pevide/cotovelo raiado",
        "prep": null
      },
      {
        "qty": null,
        "unit": null,
        "name": "a base clássica: 1 cebola roxa",
        "prep": null
      },
      {
        "qty": "1",
        "unit": null,
        "name": "malga de couve galega ou lombarda",
        "prep": "em tiras, sem os talos mais grossos"
      },
      {
        "qty": null,
        "unit": null,
        "name": "tomate",
        "prep": "picado, pimentão doce, caldo vegetal forte"
      }
    ],
    "instructions": [
      "Para a profundidade rústica do campo: refogue demorado o azeite, a cebola e o alho e espolete uma colher de pimentão. Verta o tomate cru até virar compota e adicione a couve.",
      "Encha a panela fartamente com 1 litro de água com caldo vegetal. Quando levantarem grandes borbulhas (uns 10 minutos), deposite a massa crua dentro.",
      "Deixe cozer a massa durante 10 minutos. Só 2 minutos antes do final junte o grão cozido, apenas para que absorva superficialmente o sabor do molho denso.",
      "Este prato termina com bastante molho caldoso — nunca enxuto."
    ],
    "baby_adaptation": "O macarronete comprido é ouro de exploração ao tacto para os mais pequenos. Se a criança tiver apenas 10 meses, esmague bem o grão antes de servir.",
    "pingo_doce_link": "https://www.pingodoce.pt/on/demandware.store/Sites-pingo-doce-Site/default/Search-Show?q=Rancho"
  },
  {
    "id": 30,
    "title": "Omelete Alta de Forno com Espinafres Escondidos",
    "category": "Base de Leguminosas / Vegetariano",
    "origin": "Portuguesa",
    "dynamics": [
      "Uma Panela",
      "Express"
    ],
    "time": "25 min",
    "ingredients": [
      {
        "qty": "6",
        "unit": null,
        "name": "ovos",
        "prep": "tamanho XL"
      },
      {
        "qty": "1",
        "unit": null,
        "name": "embalagem generosa de espinafres ou folhas de acelga",
        "prep": null
      },
      {
        "qty": "1",
        "unit": null,
        "name": "queijo macio do dia ou ricotta densa",
        "prep": "+/- 200g"
      },
      {
        "qty": "1",
        "unit": null,
        "name": "fio de nata magra ou leite gordo",
        "prep": null
      }
    ],
    "instructions": [
      "Passo essencial da frittata que salva omeletes escorridas: numa frigideira sem gordura, sue os espinafres crus durante 1 minuto com uma pitada de sal até cederem de tamanho e largarem a água. Escorra essa água.",
      "Bata levemente os ovos com um pingo de leite ou natas. Desfaça o queijo fresco ou a ricotta em pedaços pelas mãos e polvilhe com orégãos secos.",
      "Misture os espinafres bem escorridos e secos no banho de ovo.",
      "Deite numa travessa média forrada e untada com azeite. Leve ao forno a 180 °C até a superfície estufar e tostar ligeiramente (15 a 18 minutos)."
    ],
    "baby_adaptation": "Um fabuloso bolo macio de proteína e cálcio, sem qualquer frito em óleo. Um quadradinho perfeito cabe exatamente na medida da pinça dos dedos do bebé e enche o aporte nutricional sem necessidade de mastigação dentária.",
    "pingo_doce_link": "https://www.pingodoce.pt/on/demandware.store/Sites-pingo-doce-Site/default/Search-Show?q=Omelete+de+Forno"
  }
]
